daglint/__init__.py
daglint/cli.py
daglint/config.py
daglint/linter.py
daglint/models.py
daglint/rules/__init__.py
daglint/rules/base.py
daglint/rules/configuration.py
daglint/rules/naming.py
daglint/rules/validation.py
daglint/rules/metadata/__init__.py
daglint/rules/metadata/owner_validation.py
daglint/rules/metadata/required_dag_params.py
daglint/rules/metadata/tag_requirements.py
daglint-0.6.2.dist-info/licenses/LICENSE
daglint-0.6.2.dist-info/METADATA
daglint-0.6.2.dist-info/WHEEL
daglint-0.6.2.dist-info/entry_points.txt
daglint-0.6.2.dist-info/top_level.txt
daglint-0.6.2.dist-info/RECORD
