Metadata-Version: 2.4
Name: daglint
Version: 0.6.2
Summary: A linting tool for Apache Airflow DAG files
Author-email: Jon Morgan <morgan.jon@gmail.com>
License: MIT License
Project-URL: Homepage, https://github.com/why-pengo/daglint
Project-URL: Repository, https://github.com/why-pengo/daglint
Keywords: airflow,dag,lint,linting,static analysis,code quality
Classifier: License :: OSI Approved :: MIT License
Classifier: Development Status :: 3 - Alpha
Classifier: Intended Audience :: Developers
Classifier: Topic :: Software Development :: Quality Assurance
Classifier: Programming Language :: Python :: 3
Classifier: Programming Language :: Python :: 3.9
Classifier: Programming Language :: Python :: 3.10
Classifier: Programming Language :: Python :: 3.11
Requires-Python: >=3.9
License-File: LICENSE
Requires-Dist: click>=8.0.0
Requires-Dist: pyyaml>=5.4.0
Requires-Dist: colorama>=0.4.4
Provides-Extra: dev
Requires-Dist: pytest>=7.0.0; extra == "dev"
Requires-Dist: pytest-cov>=3.0.0; extra == "dev"
Requires-Dist: black>=22.0.0; extra == "dev"
Requires-Dist: flake8>=4.0.0; extra == "dev"
Requires-Dist: mypy>=0.950; extra == "dev"
Requires-Dist: isort>=5.10.0; extra == "dev"
Requires-Dist: setuptools>=65.0.0; extra == "dev"
Requires-Dist: build>=0.10.0; extra == "dev"
Requires-Dist: wheel>=0.38.0; extra == "dev"
Requires-Dist: bumpver>=2023.1126; extra == "dev"
Requires-Dist: twine>=4.0.0; extra == "dev"
Dynamic: license-file
